gym_adserver/__init__.py
gym_adserver/envs/__init__.py
gym_adserver/envs/ad.py
gym_adserver/envs/adserver.py
tests/__init__.py
tests/env/__init__.py
tests/env/test_ad.py
tests/env/test_adserver.py
gym_adserver-1.0.2.dist-info/LICENSE
gym_adserver-1.0.2.dist-info/METADATA
gym_adserver-1.0.2.dist-info/WHEEL
gym_adserver-1.0.2.dist-info/top_level.txt
gym_adserver-1.0.2.dist-info/RECORD
