Metadata-Version: 2.1
Name: gym-adserver
Version: 1.0.2
Summary: An OpenAI gym environment for ad serving algorithms.
Home-page: https://github.com/falox/gym-adserver
Author: Alberto Falossi
License: MIT
Keywords: openai,openai-gym,gym,environment,agent,rl,ads
Platform: UNKNOWN
Classifier: Operating System :: OS Independent
Classifier: License :: OSI Approved :: MIT License
Classifier: Programming Language :: Python :: 3
Classifier: Programming Language :: Python :: 3.4
Classifier: Programming Language :: Python :: 3.5
Classifier: Programming Language :: Python :: 3.6
Classifier: Programming Language :: Python :: 3.7
Classifier: Programming Language :: Python :: 3.8
Requires-Python: >=3.6
Requires-Dist: gym
Requires-Dist: joblib
Requires-Dist: numpy
Requires-Dist: matplotlib
Requires-Dist: pytest
Requires-Dist: pytest-cov
Requires-Dist: codecov
